modelzipper/__init__.py
modelzipper/eval.py
modelzipper/tutils.py
modelzipper/datamanager/__init__.py
modelzipper/evalmanager/__init__.py
modelzipper/evalmanager/eval.py
modelzipper/modelmanager/__init__.py
modelzipper-0.2.5.dist-info/LICENSE
modelzipper-0.2.5.dist-info/METADATA
modelzipper-0.2.5.dist-info/WHEEL
modelzipper-0.2.5.dist-info/top_level.txt
modelzipper-0.2.5.dist-info/RECORD
